easypg.py
ez-pg.py
ez_pg.py
ez_pg-1.1.2.dist-info/LICENSE
ez_pg-1.1.2.dist-info/METADATA
ez_pg-1.1.2.dist-info/WHEEL
ez_pg-1.1.2.dist-info/top_level.txt
ez_pg-1.1.2.dist-info/RECORD
