Metadata-Version: 2.1
Name: ez-pg
Version: 1.1.2
Summary: Query Builder to simplify working in postgres databases using Psycopg2
Home-page: UNKNOWN
Author: Adam Weaver
License: UNKNOWN
Platform: UNKNOWN
Classifier: Programming Language :: Python :: 3
Classifier: License :: OSI Approved :: GNU General Public License v3 (GPLv3)
Classifier: Operating System :: OS Independent
Requires-Python: >=3.6
Requires-Dist: psycopg2
